[{"city":"Toshkent","district":"Shayhontohur","street":"Zargarlik","apartmentNumber":"3/1","id":"daef623c-4a8c-4e02-8370-32bafa9d822e"},{"city":"Toshkent","district":"Yakkasaroy","street":"Shota Rustaveli","apartmentNumber":"152-A","id":"09f2b653-a676-495f-ac24-ca13c7d32674"},{"city":"Toshkent","district":"Yangihayot","street":"Sohil bo\u0027yi","apartmentNumber":"55","id":"93389e40-59c0-4f65-b3a9-5e1b870def60"},{"city":"Toshkent","district":"Chilonzor","street":"Gavhar","apartmentNumber":"70","id":"1d703a3c-985c-4f94-a7f5-7d8b93cdceae"},{"city":"Toshkent","district":"Sergeli","street":"Yangi Sergeli yo\u0027li","apartmentNumber":"56","id":"4f9ee1d6-0ab8-4c00-a92c-78bd34096116"},{"city":"Toshkent","district":"Yunusobod","street":"Amir Temur","apartmentNumber":"77-A","id":"bb938c91-d61d-432a-94ca-d592bfb9793f"},{"city":"Toshkent","district":"Mirobod","street":"Turkiston","apartmentNumber":"12-A","id":"9ed001d2-9928-4940-8a1b-2757f144acc7"},{"city":"Toshkent","district":"Shayhantohur","street":"Kichik xalqa yo\u0027li","apartmentNumber":"3","id":"3c837d27-8bb2-42ac-9a5c-07d53b867df0"},{"city":"Toshkent","district":"Yashnabod","street":"Elbek","apartmentNumber":"61","id":"21f63d0d-068d-4b00-ad85-8536ecbb3e9e"},{"city":"Toshkent","district":"Yashnabod","street":"Ohangaron","apartmentNumber":"1","id":"ebc02848-831f-4eaf-831b-d43c20db76d3"}]
